{
  "book_title": "Aeschylus' Prometheus Bound and the Seven Against Thebes by Aeschylus",
  "genre": "Mythology",
  "pkl_stem": "Aeschylus__Prometheus_Bound_and_the_Seven_Against_Thebes_by_Aeschylus",
  "top_keywords": [
    {
      "word": "blomfield",
      "score": 0.101663
    },
    {
      "word": "dindorf",
      "score": 0.098179
    },
    {
      "word": "griffiths",
      "score": 0.087957
    },
    {
      "word": "vul",
      "score": 0.085652
    },
    {
      "word": "burges",
      "score": 0.084058
    },
    {
      "word": "linwood",
      "score": 0.082346
    },
    {
      "word": "eteocles",
      "score": 0.077529
    },
    {
      "word": "erinnys",
      "score": 0.076286
    },
    {
      "word": "sqq",
      "score": 0.075074
    },
    {
      "word": "paley",
      "score": 0.074248
    },
    {
      "word": "soph",
      "score": 0.071934
    },
    {
      "word": "antig",
      "score": 0.071132
    },
    {
      "word": "nonnus",
      "score": 0.071132
    },
    {
      "word": "ism",
      "score": 0.069275
    },
    {
      "word": "ismene",
      "score": 0.067787
    },
    {
      "word": "antigone",
      "score": 0.066207
    },
    {
      "word": "polynices",
      "score": 0.064656
    },
    {
      "word": "schylus",
      "score": 0.064385
    },
    {
      "word": "jelf",
      "score": 0.062366
    },
    {
      "word": "prometheus",
      "score": 0.062246
    }
  ]
}