{
  "book_title": "Dancing Devil range by W. C. Tuttle",
  "genre": "Western Stories",
  "pkl_stem": "Dancing_Devil_range_by_W__C__Tuttle",
  "top_keywords": [
    {
      "word": "chiquita",
      "score": 0.166099
    },
    {
      "word": "yuh",
      "score": 0.162114
    },
    {
      "word": "colton",
      "score": 0.150595
    },
    {
      "word": "oren",
      "score": 0.150145
    },
    {
      "word": "frenchy",
      "score": 0.136816
    },
    {
      "word": "staley",
      "score": 0.130729
    },
    {
      "word": "blakely",
      "score": 0.127152
    },
    {
      "word": "andy",
      "score": 0.125333
    },
    {
      "word": "hartley",
      "score": 0.120597
    },
    {
      "word": "regan",
      "score": 0.11273
    },
    {
      "word": "morales",
      "score": 0.112405
    },
    {
      "word": "judy",
      "score": 0.110218
    },
    {
      "word": "yeah",
      "score": 0.10251
    },
    {
      "word": "gus",
      "score": 0.102006
    },
    {
      "word": "nell",
      "score": 0.101018
    },
    {
      "word": "davidson",
      "score": 0.093684
    },
    {
      "word": "johnny",
      "score": 0.088854
    },
    {
      "word": "nolan",
      "score": 0.085772
    },
    {
      "word": "tomahawk",
      "score": 0.084293
    },
    {
      "word": "stableman",
      "score": 0.082053
    }
  ]
}