{
  "book_title": "The basic facts of economics : A common-sense primer for advanced students by Post",
  "genre": "Political Economy",
  "pkl_stem": "The_basic_facts_of_economics___A_common_sense_primer_for_advanced_students_by_Post",
  "top_keywords": [
    {
      "word": "economics",
      "score": 0.094962
    },
    {
      "word": "allocation",
      "score": 0.093741
    },
    {
      "word": "allocated",
      "score": 0.080854
    },
    {
      "word": "economic",
      "score": 0.076972
    },
    {
      "word": "basic",
      "score": 0.075301
    },
    {
      "word": "allocations",
      "score": 0.07341
    },
    {
      "word": "interchanges",
      "score": 0.073202
    },
    {
      "word": "specialization",
      "score": 0.071446
    },
    {
      "word": "desirability",
      "score": 0.069369
    },
    {
      "word": "specialties",
      "score": 0.067146
    },
    {
      "word": "categories",
      "score": 0.067122
    },
    {
      "word": "category",
      "score": 0.063634
    },
    {
      "word": "classifications",
      "score": 0.063475
    },
    {
      "word": "consumers",
      "score": 0.061425
    },
    {
      "word": "commodities",
      "score": 0.059165
    },
    {
      "word": "producers",
      "score": 0.057898
    },
    {
      "word": "colloquial",
      "score": 0.057545
    },
    {
      "word": "distributive",
      "score": 0.057298
    },
    {
      "word": "locations",
      "score": 0.057298
    },
    {
      "word": "labor",
      "score": 0.056112
    }
  ]
}