{
  "book_title": "The Confessions of St. Augustine by Bishop of Hippo Saint Augustine",
  "genre": "Metaphysics and Epistemology",
  "pkl_stem": "The_Confessions_of_St__Augustine_by_Bishop_of_Hippo_Saint_Augustine",
  "top_keywords": [
    {
      "word": "madest",
      "score": 0.07573
    },
    {
      "word": "continency",
      "score": 0.065545
    },
    {
      "word": "formlessness",
      "score": 0.060251
    },
    {
      "word": "victorinus",
      "score": 0.059484
    },
    {
      "word": "unchangeably",
      "score": 0.05922
    },
    {
      "word": "wouldest",
      "score": 0.055731
    },
    {
      "word": "willeth",
      "score": 0.051574
    },
    {
      "word": "confesseth",
      "score": 0.050284
    },
    {
      "word": "corporeal",
      "score": 0.049761
    },
    {
      "word": "saidst",
      "score": 0.04882
    },
    {
      "word": "concupiscence",
      "score": 0.047778
    },
    {
      "word": "commandest",
      "score": 0.047246
    },
    {
      "word": "gavest",
      "score": 0.047082
    },
    {
      "word": "joyed",
      "score": 0.046851
    },
    {
      "word": "hadst",
      "score": 0.046827
    },
    {
      "word": "shouldest",
      "score": 0.045769
    },
    {
      "word": "didst",
      "score": 0.045767
    },
    {
      "word": "heardest",
      "score": 0.045712
    },
    {
      "word": "leasing",
      "score": 0.045712
    },
    {
      "word": "rejoiceth",
      "score": 0.045505
    }
  ]
}