{
  "book_title": "The Fortune Hunter by Louis Joseph Vance and Winchell Smith",
  "genre": "NY-as-character",
  "pkl_stem": "The_Fortune_Hunter_by_Louis_Joseph_Vance_and_Winchell_Smith",
  "top_keywords": [
    {
      "word": "tracey",
      "score": 0.107603
    },
    {
      "word": "josie",
      "score": 0.102289
    },
    {
      "word": "blinky",
      "score": 0.09382
    },
    {
      "word": "kellogg",
      "score": 0.090192
    },
    {
      "word": "lockwood",
      "score": 0.088682
    },
    {
      "word": "burnham",
      "score": 0.084638
    },
    {
      "word": "duncan",
      "score": 0.08329
    },
    {
      "word": "bohun",
      "score": 0.077622
    },
    {
      "word": "roland",
      "score": 0.074074
    },
    {
      "word": "watty",
      "score": 0.072356
    },
    {
      "word": "tuthill",
      "score": 0.069993
    },
    {
      "word": "bigelow",
      "score": 0.069635
    },
    {
      "word": "sothern",
      "score": 0.069126
    },
    {
      "word": "spaulding",
      "score": 0.06749
    },
    {
      "word": "sody",
      "score": 0.066702
    },
    {
      "word": "robbins",
      "score": 0.064559
    },
    {
      "word": "graham",
      "score": 0.06323
    },
    {
      "word": "nat",
      "score": 0.062869
    },
    {
      "word": "betty",
      "score": 0.061784
    },
    {
      "word": "pete",
      "score": 0.061447
    }
  ]
}